<?xml version="1.0" encoding="UTF-8"?>
<objects serializationModel="Studio.02.02.00">
	<object class="AudioFile" id="{92d98a84-0cd9-48f2-b473-d9703a1e84bc}">
		<property name="assetPath">
			<value>CFCK WINGS SWEETENER Whoosh Windy Long.wav</value>
		</property>
		<property name="isStreaming">
			<value>true</value>
		</property>
		<property name="frequencyInKHz">
			<value>96</value>
		</property>
		<property name="channelCount">
			<value>1</value>
		</property>
		<property name="length">
			<value>25</value>
		</property>
		<relationship name="masterAssetFolder">
			<destination>{a5dc1744-e8c3-4327-8c35-87ad8b91160c}</destination>
		</relationship>
	</object>
</objects>
