<?xml version="1.0" encoding="UTF-8"?>
<objects serializationModel="Studio.02.02.00">
	<object class="Event" id="{39123bcf-6f7e-48eb-a5ef-2be4b7060d78}">
		<property name="color">
			<value>Green</value>
		</property>
		<property name="name">
			<value>sliders</value>
		</property>
		<property name="outputFormat">
			<value>1</value>
		</property>
		<relationship name="folder">
			<destination>{62f0bb78-ad25-4f5f-be96-f8394901ca93}</destination>
		</relationship>
		<relationship name="mixer">
			<destination>{0451d2d9-8fea-43d7-894e-4d0aa01925cd}</destination>
		</relationship>
		<relationship name="masterTrack">
			<destination>{d9d007dc-e211-48a3-a930-1cec3b68bf5b}</destination>
		</relationship>
		<relationship name="mixerInput">
			<destination>{91c85625-75c2-41b2-8148-f798c5d6c488}</destination>
		</relationship>
		<relationship name="automatableProperties">
			<destination>{6f487799-438d-4762-aafa-35fb8a5eb716}</destination>
		</relationship>
		<relationship name="markerTracks">
			<destination>{bf0f948d-db53-41b0-8f8a-d52248eb95b7}</destination>
		</relationship>
		<relationship name="groupTracks">
			<destination>{9d8df6c4-5d00-4155-a018-be2b09f2f70c}</destination>
		</relationship>
		<relationship name="timeline">
			<destination>{5fb900fe-2748-4465-97a0-41e9b70b10cf}</destination>
		</relationship>
		<relationship name="parameters">
			<destination>{178ad271-f16c-4d24-b58e-b0e7bccbac4a}</destination>
		</relationship>
		<relationship name="banks">
			<destination>{903cfe6e-e297-4164-b8d0-4abf911ffd12}</destination>
		</relationship>
	</object>
	<object class="EventMixer" id="{0451d2d9-8fea-43d7-894e-4d0aa01925cd}">
		<relationship name="masterBus">
			<destination>{8014ae19-640e-4775-8e20-d61dd13fbec3}</destination>
		</relationship>
	</object>
	<object class="MasterTrack" id="{d9d007dc-e211-48a3-a930-1cec3b68bf5b}">
		<relationship name="mixerGroup">
			<destination>{8014ae19-640e-4775-8e20-d61dd13fbec3}</destination>
		</relationship>
	</object>
	<object class="MixerInput" id="{91c85625-75c2-41b2-8148-f798c5d6c488}">
		<relationship name="effectChain">
			<destination>{d6005372-e056-493a-b83a-88c8efc7aa96}</destination>
		</relationship>
		<relationship name="panner">
			<destination>{88c71f85-4359-4e32-946d-b74df4d8452e}</destination>
		</relationship>
		<relationship name="output">
			<destination>{8638b0ec-f383-4d23-87aa-5bbfa74c9c15}</destination>
		</relationship>
	</object>
	<object class="EventAutomatableProperties" id="{6f487799-438d-4762-aafa-35fb8a5eb716}">
		<property name="isPersistent">
			<value>true</value>
		</property>
	</object>
	<object class="MarkerTrack" id="{bf0f948d-db53-41b0-8f8a-d52248eb95b7}" />
	<object class="GroupTrack" id="{9d8df6c4-5d00-4155-a018-be2b09f2f70c}">
		<relationship name="modules">
			<destination>{ab0d69f6-3893-4696-b7f0-fa0005d4f947}</destination>
		</relationship>
		<relationship name="mixerGroup">
			<destination>{3dd48db5-55c4-4316-98fc-ae8a23751176}</destination>
		</relationship>
	</object>
	<object class="Timeline" id="{5fb900fe-2748-4465-97a0-41e9b70b10cf}">
		<relationship name="markers">
			<destination>{f0fcce84-7033-408d-8b3a-65cc8840ef52}</destination>
		</relationship>
	</object>
	<object class="ParameterProxy" id="{178ad271-f16c-4d24-b58e-b0e7bccbac4a}">
		<relationship name="modules">
			<destination>{ab0d69f6-3893-4696-b7f0-fa0005d4f947}</destination>
		</relationship>
		<relationship name="preset">
			<destination>{5f77658d-cf74-4f4f-a4ba-ce4dd383a3e9}</destination>
		</relationship>
	</object>
	<object class="EventMixerMaster" id="{8014ae19-640e-4775-8e20-d61dd13fbec3}">
		<relationship name="effectChain">
			<destination>{991710a5-3d30-4889-9b35-80091bb26830}</destination>
		</relationship>
		<relationship name="panner">
			<destination>{5e16820e-be33-4c17-888b-e1b2687361b7}</destination>
		</relationship>
		<relationship name="mixer">
			<destination>{0451d2d9-8fea-43d7-894e-4d0aa01925cd}</destination>
		</relationship>
	</object>
	<object class="MixerBusEffectChain" id="{d6005372-e056-493a-b83a-88c8efc7aa96}">
		<relationship name="effects">
			<destination>{b021eb66-363c-4081-9b2c-eb0b172c860a}</destination>
		</relationship>
	</object>
	<object class="MixerBusPanner" id="{88c71f85-4359-4e32-946d-b74df4d8452e}" />
	<object class="SingleSound" id="{ab0d69f6-3893-4696-b7f0-fa0005d4f947}">
		<property name="isCutoff">
			<value>true</value>
		</property>
		<property name="start">
			<value>0.90000000000000002</value>
		</property>
		<property name="length">
			<value>0.099999999999999534</value>
		</property>
		<property name="volume">
			<value>-24.5</value>
		</property>
		<property name="looping">
			<value>true</value>
		</property>
		<relationship name="modulators">
			<destination>{cd6b27be-e841-4348-8f03-5da055fffbac}</destination>
		</relationship>
		<relationship name="audioFile">
			<destination>{e965d0e7-68ff-4aaa-b4e3-6ccff40a042e}</destination>
		</relationship>
	</object>
	<object class="EventMixerGroup" id="{3dd48db5-55c4-4316-98fc-ae8a23751176}">
		<property name="volume">
			<value>-33</value>
		</property>
		<property name="name">
			<value>Audio 1</value>
		</property>
		<relationship name="effectChain">
			<destination>{12570c32-40ce-4918-82b0-d04b727779aa}</destination>
		</relationship>
		<relationship name="panner">
			<destination>{b4f43816-c174-419d-9aa6-27e3095e4343}</destination>
		</relationship>
		<relationship name="output">
			<destination>{8014ae19-640e-4775-8e20-d61dd13fbec3}</destination>
		</relationship>
	</object>
	<object class="LoopRegion" id="{f0fcce84-7033-408d-8b3a-65cc8840ef52}">
		<property name="position">
			<value>0</value>
		</property>
		<property name="length">
			<value>3.8186666666666667</value>
		</property>
		<relationship name="timeline">
			<destination>{5fb900fe-2748-4465-97a0-41e9b70b10cf}</destination>
		</relationship>
		<relationship name="markerTrack">
			<destination>{bf0f948d-db53-41b0-8f8a-d52248eb95b7}</destination>
		</relationship>
	</object>
	<object class="MixerBusEffectChain" id="{991710a5-3d30-4889-9b35-80091bb26830}">
		<relationship name="effects">
			<destination>{6bebab85-e255-4bc8-bf3d-1f23084b24a2}</destination>
		</relationship>
	</object>
	<object class="MixerBusPanner" id="{5e16820e-be33-4c17-888b-e1b2687361b7}" />
	<object class="MixerBusFader" id="{b021eb66-363c-4081-9b2c-eb0b172c860a}" />
	<object class="ADSRModulator" id="{cd6b27be-e841-4348-8f03-5da055fffbac}">
		<property name="nameOfPropertyBeingModulated">
			<value>volume</value>
		</property>
		<property name="initialValue">
			<value>-80</value>
		</property>
		<property name="attackTime">
			<value>40</value>
		</property>
		<property name="releaseTime">
			<value>80</value>
		</property>
		<property name="finalValue">
			<value>-80</value>
		</property>
	</object>
	<object class="MixerBusEffectChain" id="{12570c32-40ce-4918-82b0-d04b727779aa}">
		<relationship name="effects">
			<destination>{02777107-d618-43f5-955e-b3c556e9c2f9}</destination>
		</relationship>
	</object>
	<object class="MixerBusPanner" id="{b4f43816-c174-419d-9aa6-27e3095e4343}" />
	<object class="MixerBusFader" id="{6bebab85-e255-4bc8-bf3d-1f23084b24a2}" />
	<object class="MixerBusFader" id="{02777107-d618-43f5-955e-b3c556e9c2f9}" />
</objects>
